facets_mcp/CLAUDE.md
facets_mcp/__init__.py
facets_mcp/_version.py
facets_mcp/config.py
facets_mcp/context.yml
facets_mcp/facets_server.py
facets_mcp/ai/initialize.md
facets_mcp/prompts/__init__.py
facets_mcp/prompts/fork_module.md
facets_mcp/prompts/fork_module_prompt.py
facets_mcp/tools/__init__.py
facets_mcp/tools/deploy_module.py
facets_mcp/tools/existing_modules.py
facets_mcp/tools/fork_module.py
facets_mcp/tools/ftf_tools.py
facets_mcp/tools/import_tools.py
facets_mcp/tools/instructions.py
facets_mcp/tools/intent_management_tools.py
facets_mcp/tools/module_files.py
facets_mcp/tools/module_instructions/artifact_inputs.md
facets_mcp/tools/module_instructions/facets_yaml_spec_x-ui_tags.md
facets_mcp/tools/module_instructions/generation_workflow.md
facets_mcp/tools/module_instructions/how_to_configure_provider.md
facets_mcp/tools/module_instructions/iac_block.md
facets_mcp/tools/module_instructions/imports.md
facets_mcp/tools/module_instructions/input_outputs.md
facets_mcp/tools/module_instructions/readme_writing.md
facets_mcp/tools/module_instructions/tf.md
facets_mcp/tools/module_instructions/variables.md
facets_mcp/utils/__init__.py
facets_mcp/utils/client_utils.py
facets_mcp/utils/file_utils.py
facets_mcp/utils/ftf_command_utils.py
facets_mcp/utils/intent_utils.py
facets_mcp/utils/module_download_utils.py
facets_mcp/utils/output_utils.py
facets_mcp/utils/validation_utils.py
facets_mcp/utils/yaml_utils.py
facets_module_mcp-0.1.20.dist-info/METADATA
facets_module_mcp-0.1.20.dist-info/WHEEL
facets_module_mcp-0.1.20.dist-info/entry_points.txt
facets_module_mcp-0.1.20.dist-info/top_level.txt
facets_module_mcp-0.1.20.dist-info/RECORD
