Metadata-Version: 2.4
Name: facets-module-mcp
Version: 0.1.20
Summary: Facets Module MCP
Author-email: Anshul Sao <anshul@facets.cloud>, Anuj Hydrabadi <anuj.hydrabadi@facets.cloud>, Sanmesh Kakade <sanmesh.kakade@facets.cloud>
License: MIT
Project-URL: Homepage, https://github.com/Facets-cloud/facets-module-mcp
Project-URL: Bug Tracker, https://github.com/Facets-cloud/facets-module-mcp/issues
Project-URL: Documentation, https://github.com/Facets-cloud/facets-module-mcp#readme
Keywords: Facets,MCP,Terraform,Python
Classifier: Programming Language :: Python :: 3
Classifier: Programming Language :: Python :: 3.11
Classifier: Programming Language :: Python :: 3.12
Classifier: Programming Language :: Python :: 3.13
Classifier: License :: OSI Approved :: MIT License
Classifier: Operating System :: OS Independent
Classifier: Topic :: Software Development :: Libraries :: Python Modules
Classifier: Topic :: Software Development :: Build Tools
Classifier: Intended Audience :: Developers
Classifier: Development Status :: 4 - Beta
Requires-Python: >=3.11
Requires-Dist: mcp[cli]
Requires-Dist: checkov
Requires-Dist: questionary
Requires-Dist: ftf-cli==0.3.4
Requires-Dist: facets-control-plane-sdk==1.0.3
Requires-Dist: facets-hcl
